Metadata-Version: 1.1
Name: djangosourcecontrol
Version: 1.1
Summary: A simple Django app to conduct create Web-based Python projects and files. Powered by KnockoutJs and django-rest-framework
Home-page: https://github.com/kull2222/DjangoSourceControl/
Author: Daniel J Pepka
Author-email: pepkad@wsu.edu
License: gpl-3.0
Platform: UNKNOWN
Classifier: Environment :: Web Environment
Classifier: Framework :: Django
Classifier: Framework :: Django :: 1.10
Classifier: Intended Audience :: Developers
Classifier: License :: OSI Approved :: BSD License
Classifier: Operating System :: OS Independent
Classifier: Programming Language :: Python
Classifier: Programming Language :: Python :: 3
Classifier: Programming Language :: Python :: 3.5
Classifier: Topic :: Internet :: WWW/HTTP
Classifier: Topic :: Internet :: WWW/HTTP :: Dynamic Content
